benchmark/andydataset/train_mlp_variations.py
benchmark/andydataset/train_simlpe_variations.py
dataset_preprocessing/andydataset_to_hdf5.py
dataset_preprocessing/h36mdataset_to_hdf5.py
dataset_preprocessing/teleopicubdataset_to_hdf5.py
docs/conf.py
examples/compare_predictors.py
examples/load_and_plot_predictor.py
examples/mlp_icub_train.py
examples/plot_pred_over_time.py
examples/promp_icub.py
examples/start_multiple_trainings.py
examples/train_from_config.py
examples/visualize_andy_ee_prediction.py
prescyent/__init__.py
prescyent/auto_dataset.py
prescyent/auto_predictor.py
prescyent/base_config.py
prescyent/dataset/__init__.py
prescyent/dataset/config.py
prescyent/dataset/datasamples.py
prescyent/dataset/dataset.py
prescyent/dataset/hdf5_datasample.py
prescyent/dataset/hdf5_utils.py
prescyent/dataset/datasets/__init__.py
prescyent/dataset/datasets/custom_dataset.py
prescyent/dataset/datasets/andydataset/__init__.py
prescyent/dataset/datasets/andydataset/config.py
prescyent/dataset/datasets/andydataset/dataset.py
prescyent/dataset/datasets/andydataset/metadata.py
prescyent/dataset/datasets/human36m/__init__.py
prescyent/dataset/datasets/human36m/config.py
prescyent/dataset/datasets/human36m/dataset.py
prescyent/dataset/datasets/human36m/metadata.py
prescyent/dataset/datasets/human36m/h36m_arm/__init__.py
prescyent/dataset/datasets/human36m/h36m_arm/config.py
prescyent/dataset/datasets/human36m/h36m_arm/dataset.py
prescyent/dataset/datasets/human36m/h36m_arm/metadata.py
prescyent/dataset/datasets/synthetic_circle_clusters/__init__.py
prescyent/dataset/datasets/synthetic_circle_clusters/config.py
prescyent/dataset/datasets/synthetic_circle_clusters/dataset.py
prescyent/dataset/datasets/synthetic_circle_clusters/metadata.py
prescyent/dataset/datasets/synthetic_simple_trajs/__init__.py
prescyent/dataset/datasets/synthetic_simple_trajs/config.py
prescyent/dataset/datasets/synthetic_simple_trajs/dataset.py
prescyent/dataset/datasets/synthetic_simple_trajs/metadata.py
prescyent-0.7.2.dist-info/LICENSE
prescyent-0.7.2.dist-info/METADATA
prescyent-0.7.2.dist-info/WHEEL
prescyent-0.7.2.dist-info/top_level.txt
prescyent-0.7.2.dist-info/RECORD
