Metadata-Version: 2.1
Name: prescyent
Version: 0.7.2
Summary: Data-driven trajectory forecasting library
Author-email: Alexis Biver <alexis.biver@inria.fr>
License: MIT
Project-URL: Documentation, https://hucebot.github.io/prescyent/
Project-URL: Repository, https://github.com/hucebot/prescyent
Project-URL: Issues, https://github.com/hucebot/prescyent/issues
Keywords: trajectory,forecasting,pytorch_lightning
Classifier: Intended Audience :: Developers
Classifier: License :: OSI Approved :: MIT License
Classifier: Programming Language :: Python
Classifier: Programming Language :: Python :: 3.8
Classifier: Programming Language :: Python :: 3.9
Classifier: Programming Language :: Python :: 3.10
Classifier: Operating System :: OS Independent
License-File: LICENSE
Requires-Dist: h5py<4,>=3.10
Requires-Dist: matplotlib<4.0,>=3.0
Requires-Dist: numpy<2.0.0,>=1.17.3
Requires-Dist: pydantic<3.0,>=2.0
Requires-Dist: pytorch_lightning<3.0,>=2.0
Requires-Dist: protobuf>=4.0
Requires-Dist: scipy<2.0,>=1.9
Requires-Dist: tensorboard<3.0,>=2.0
Requires-Dist: torch<3.0,>=2.0
Requires-Dist: tqdm>=4.66
